{"info":"%-------------------------------------------------------------------------------\n%%MatrixMarket matrix coordinate real symmetric\n%-------------------------------------------------------------------------------\n% UF Sparse Matrix Collection, Tim Davis\n% http://www.cise.ufl.edu/research/sparse/matrices/VDOL/tumorAntiAngiogenesis_1\n% name: VDOL/tumorAntiAngiogenesis_1\n% [tumorAntiAngiogenesis optimal control problem (matrix 1 of 8)]\n% id: 2748\n% date: 2015\n% author: B. Senses, A. Rao\n% ed: T. Davis\n% fields: name title A b id date author ed kind notes aux\n% aux: rowname mapping\n% kind: optimal control problem\n%-------------------------------------------------------------------------------\n% notes:\n% Optimal control problem, Vehicle Dynamics & Optimization Lab, UF       \n% Anil Rao and Begum Senses, University of Florida                       \n% http://vdol.mae.ufl.edu                                                \n%                                                                        \n% This matrix arises from an optimal control problem described below.    \n% Each optimal control problem gives rise to a sequence of matrices of   \n% different sizes when they are being solved inside GPOPS, an optimal    \n% control solver created by Anil Rao, Begum Senses, and others at in VDOL\n% lab at the University of Florida.  This is one of the matrices in one  \n% of these problems.  The matrix is symmetric indefinite.                \n%                                                                        \n% Rao, Senses, and Davis have created a graph coarsening strategy        \n% that matches pairs of nodes.  The mapping is given for this matrix,    \n% where map(i)=k means that node i in the original graph is mapped to    \n% node k in the smaller graph.  map(i)=map(j)=k means that both nodes    \n% i and j are mapped to the same node k, and thus nodes i and j have     \n% been merged.                                                           \n%                                                                        \n% This matrix consists of a set of nodes (rows/columns) and the          \n% names of these rows/cols are given                                     \n%                                                                        \n% Anil Rao, Begum Sense, and Tim Davis, 2015.                            \n%                                                                        \n% VDOL/tumorAntiogenesis                                                 \n%                                                                        \n% Tumor anti-angiogenesis optimal control problem is taken from          \n% Ref.~\\cite{ledzewicz2008analysis}. A tumor first uses the blood        \n% vessels of its host but as the tumor grows oxygen that is carried by   \n% the blood vessels of its host cannot defuse very far into the tumor.   \n% Therefore, the tumor grows its own blood vessels by producing          \n% vascular endothelial growth factor (VEGF). This process is called      \n% angiogenesis. But blood vessels have a defense mechanism, called       \n% endostatin, that tries to impede the development of new blood cells    \n% by targeting VEGF. In addition, new pharmacological therapies that is  \n% developed for tumor-type cancers also targets VEGF. The goal of the    \n% tumor anti-angiogenesis problem is to determine the state and control  \n% that minimizing the size of the tumor at the final time. The state of  \n% the system is defined by the tumor volume, carrying capacity of a      \n% vessel, and the total anti-angiogenic treatment administered and the   \n% control of the system is the angiogenic dose rate.  The specified      \n% accuracy tolerance of $10^{-7}$ were satisfied after eight mesh        \n% iterations. As the mesh refinement proceeds, the size of the KKT       \n% matrices increases from 205 to 490.                                    \n%                                                                        \n% @article{ledzewicz2008analysis,                                        \n%   title={Analysis of Optimal Controls for a Mathematical Model of      \n%      Tumour Anti-Angiogenesis},                                        \n%   author={Ledzewicz, Urszula and Sch{\\\"a}ttler, Heinz},                \n%   journal={Optimal Control Applications and Methods},                  \n%   volume=29,                                                           \n%   number=1,                                                            \n%   pages={41--57},                                                      \n%   year=2008,                                                           \n%   publisher={Wiley Online Library}                                     \n% }                                                                      \n","meta":{"rows":"205","cols":"205","value":"205","rowIndex":"source","colIndex":"target"},"data":[{"source":0,"target":0,"value":1},{"source":40,"target":0,"value":1},{"source":120,"target":0,"value":1},{"source":123,"target":0,"value":1},{"source":124,"target":0,"value":1},{"source":125,"target":0,"value":1},{"source":126,"target":0,"value":1},{"source":164,"target":0,"value":1},{"source":1,"target":1,"value":2},{"source":41,"target":1,"value":2},{"source":120,"target":1,"value":2},{"source":123,"target":1,"value":2},{"source":124,"target":1,"value":2},{"source":125,"target":1,"value":2},{"source":126,"target":1,"value":2},{"source":165,"target":1,"value":2},{"source":2,"target":2,"value":3},{"source":42,"target":2,"value":3},{"source":120,"target":2,"value":3},{"source":123,"target":2,"value":3},{"source":124,"target":2,"value":3},{"source":125,"target":2,"value":3},{"source":126,"target":2,"value":3},{"source":166,"target":2,"value":3},{"source":3,"target":3,"value":4},{"source":43,"target":3,"value":4},{"source":120,"target":3,"value":4},{"source":123,"target":3,"value":4},{"source":124,"target":3,"value":4},{"source":125,"target":3,"value":4},{"source":126,"target":3,"value":4},{"source":127,"target":3,"value":4},{"source":128,"target":3,"value":4},{"source":129,"target":3,"value":4},{"source":130,"target":3,"value":4},{"source":167,"target":3,"value":4},{"source":4,"target":4,"value":5},{"source":44,"target":4,"value":5},{"source":120,"target":4,"value":5},{"source":127,"target":4,"value":5},{"source":128,"target":4,"value":5},{"source":129,"target":4,"value":5},{"source":130,"target":4,"value":5},{"source":168,"target":4,"value":5},{"source":5,"target":5,"value":6},{"source":45,"target":5,"value":6},{"source":120,"target":5,"value":6},{"source":127,"target":5,"value":6},{"source":128,"target":5,"value":6},{"source":129,"target":5,"value":6},{"source":130,"target":5,"value":6},{"source":169,"target":5,"value":6},{"source":6,"target":6,"value":7},{"source":46,"target":6,"value":7},{"source":120,"target":6,"value":7},{"source":127,"target":6,"value":7},{"source":128,"target":6,"value":7},{"source":129,"target":6,"value":7},{"source":130,"target":6,"value":7},{"source":170,"target":6,"value":7},{"source":7,"target":7,"value":8},{"source":47,"target":7,"value":8},{"source":120,"target":7,"value":8},{"source":127,"target":7,"value":8},{"source":128,"target":7,"value":8},{"source":129,"target":7,"value":8},{"source":130,"target":7,"value":8},{"source":131,"target":7,"value":8},{"source":132,"target":7,"value":8},{"source":133,"target":7,"value":8},{"source":134,"target":7,"value":8},{"source":171,"target":7,"value":8},{"source":8,"target":8,"value":9},{"source":48,"target":8,"value":9},{"source":120,"target":8,"value":9},{"source":131,"target":8,"value":9},{"source":132,"target":8,"value":9},{"source":133,"target":8,"value":9},{"source":134,"target":8,"value":9},{"source":172,"target":8,"value":9},{"source":9,"target":9,"value":10},{"source":49,"target":9,"value":10},{"source":120,"target":9,"value":10},{"source":131,"target":9,"value":10},{"source":132,"target":9,"value":10},{"source":133,"target":9,"value":10},{"source":134,"target":9,"value":10},{"source":173,"target":9,"value":10},{"source":10,"target":10,"value":11},{"source":50,"target":10,"value":11},{"source":120,"target":10,"value":11},{"source":131,"target":10,"value":11},{"source":132,"target":10,"value":11},{"source":133,"target":10,"value":11},{"source":134,"target":10,"value":11},{"source":174,"target":10,"value":11},{"source":11,"target":11,"value":12},{"source":51,"target":11,"value":12},{"source":120,"target":11,"value":12},{"source":131,"target":11,"value":12},{"source":132,"target":11,"value":12},{"source":133,"target":11,"value":12},{"source":134,"target":11,"value":12},{"source":135,"target":11,"value":12},{"source":136,"target":11,"value":12},{"source":137,"target":11,"value":12},{"source":138,"target":11,"value":12},{"source":175,"target":11,"value":12},{"source":12,"target":12,"value":13},{"source":52,"target":12,"value":13},{"source":120,"target":12,"value":13},{"source":135,"target":12,"value":13},{"source":136,"target":12,"value":13},{"source":137,"target":12,"value":13},{"source":138,"target":12,"value":13},{"source":176,"target":12,"value":13},{"source":13,"target":13,"value":14},{"source":53,"target":13,"value":14},{"source":120,"target":13,"value":14},{"source":135,"target":13,"value":14},{"source":136,"target":13,"value":14},{"source":137,"target":13,"value":14},{"source":138,"target":13,"value":14},{"source":177,"target":13,"value":14},{"source":14,"target":14,"value":15},{"source":54,"target":14,"value":15},{"source":120,"target":14,"value":15},{"source":135,"target":14,"value":15},{"source":136,"target":14,"value":15},{"source":137,"target":14,"value":15},{"source":138,"target":14,"value":15},{"source":178,"target":14,"value":15},{"source":15,"target":15,"value":16},{"source":55,"target":15,"value":16},{"source":120,"target":15,"value":16},{"source":135,"target":15,"value":16},{"source":136,"target":15,"value":16},{"source":137,"target":15,"value":16},{"source":138,"target":15,"value":16},{"source":139,"target":15,"value":16},{"source":140,"target":15,"value":16},{"source":141,"target":15,"value":16},{"source":142,"target":15,"value":16},{"source":179,"target":15,"value":16},{"source":16,"target":16,"value":17},{"source":56,"target":16,"value":17},{"source":120,"target":16,"value":17},{"source":139,"target":16,"value":17},{"source":140,"target":16,"value":17},{"source":141,"target":16,"value":17},{"source":142,"target":16,"value":17},{"source":180,"target":16,"value":17},{"source":17,"target":17,"value":18},{"source":57,"target":17,"value":18},{"source":120,"target":17,"value":18},{"source":139,"target":17,"value":18},{"source":140,"target":17,"value":18},{"source":141,"target":17,"value":18},{"source":142,"target":17,"value":18},{"source":181,"target":17,"value":18},{"source":18,"target":18,"value":19},{"source":58,"target":18,"value":19},{"source":120,"target":18,"value":19},{"source":139,"target":18,"value":19},{"source":140,"target":18,"value":19},{"source":141,"target":18,"value":19},{"source":142,"target":18,"value":19},{"source":182,"target":18,"value":19},{"source":19,"target":19,"value":20},{"source":59,"target":19,"value":20},{"source":120,"target":19,"value":20},{"source":139,"target":19,"value":20},{"source":140,"target":19,"value":20},{"source":141,"target":19,"value":20},{"source":142,"target":19,"value":20},{"source":143,"target":19,"value":20},{"source":144,"target":19,"value":20},{"source":145,"target":19,"value":20},{"source":146,"target":19,"value":20},{"source":183,"target":19,"value":20},{"source":20,"target":20,"value":21},{"source":60,"target":20,"value":21},{"source":120,"target":20,"value":21},{"source":143,"target":20,"value":21},{"source":144,"target":20,"value":21},{"source":145,"target":20,"value":21},{"source":146,"target":20,"value":21},{"source":184,"target":20,"value":21},{"source":21,"target":21,"value":22},{"source":61,"target":21,"value":22},{"source":120,"target":21,"value":22},{"source":143,"target":21,"value":22},{"source":144,"target":21,"value":22},{"source":145,"target":21,"value":22},{"source":146,"target":21,"value":22},{"source":185,"target":21,"value":22},{"source":22,"target":22,"value":23},{"source":62,"target":22,"value":23},{"source":120,"target":22,"value":23},{"source":143,"target":22,"value":23},{"source":144,"target":22,"value":23},{"source":145,"target":22,"value":23},{"source":146,"target":22,"value":23},{"source":186,"target":22,"value":23},{"source":23,"target":23,"value":24},{"source":63,"target":23,"value":24},{"source":120,"target":23,"value":24},{"source":143,"target":23,"value":24},{"source":144,"target":23,"value":24},{"source":145,"target":23,"value":24},{"source":146,"target":23,"value":24},{"source":147,"target":23,"value":24},{"source":148,"target":23,"value":24},{"source":149,"target":23,"value":24},{"source":150,"target":23,"value":24},{"source":187,"target":23,"value":24},{"source":24,"target":24,"value":25},{"source":64,"target":24,"value":25},{"source":120,"target":24,"value":25},{"source":147,"target":24,"value":25},{"source":148,"target":24,"value":25},{"source":149,"target":24,"value":25},{"source":150,"target":24,"value":25},{"source":188,"target":24,"value":25},{"source":25,"target":25,"value":26},{"source":65,"target":25,"value":26},{"source":120,"target":25,"value":26},{"source":147,"target":25,"value":26},{"source":148,"target":25,"value":26},{"source":149,"target":25,"value":26},{"source":150,"target":25,"value":26},{"source":189,"target":25,"value":26},{"source":26,"target":26,"value":27},{"source":66,"target":26,"value":27},{"source":120,"target":26,"value":27},{"source":147,"target":26,"value":27},{"source":148,"target":26,"value":27},{"source":149,"target":26,"value":27},{"source":150,"target":26,"value":27},{"source":190,"target":26,"value":27},{"source":27,"target":27,"value":28},{"source":67,"target":27,"value":28},{"source":120,"target":27,"value":28},{"source":147,"target":27,"value":28},{"source":148,"target":27,"value":28},{"source":149,"target":27,"value":28},{"source":150,"target":27,"value":28},{"source":151,"target":27,"value":28},{"source":152,"target":27,"value":28},{"source":153,"target":27,"value":28},{"source":154,"target":27,"value":28},{"source":191,"target":27,"value":28},{"source":28,"target":28,"value":29},{"source":68,"target":28,"value":29},{"source":120,"target":28,"value":29},{"source":151,"target":28,"value":29},{"source":152,"target":28,"value":29},{"source":153,"target":28,"value":29},{"source":154,"target":28,"value":29},{"source":192,"target":28,"value":29},{"source":29,"target":29,"value":30},{"source":69,"target":29,"value":30},{"source":120,"target":29,"value":30},{"source":151,"target":29,"value":30},{"source":152,"target":29,"value":30},{"source":153,"target":29,"value":30},{"source":154,"target":29,"value":30},{"source":193,"target":29,"value":30},{"source":30,"target":30,"value":31},{"source":70,"target":30,"value":31},{"source":120,"target":30,"value":31},{"source":151,"target":30,"value":31},{"source":152,"target":30,"value":31},{"source":153,"target":30,"value":31},{"source":154,"target":30,"value":31},{"source":194,"target":30,"value":31},{"source":31,"target":31,"value":32},{"source":71,"target":31,"value":32},{"source":120,"target":31,"value":32},{"source":151,"target":31,"value":32},{"source":152,"target":31,"value":32},{"source":153,"target":31,"value":32},{"source":154,"target":31,"value":32},{"source":155,"target":31,"value":32},{"source":156,"target":31,"value":32},{"source":157,"target":31,"value":32},{"source":158,"target":31,"value":32},{"source":195,"target":31,"value":32},{"source":32,"target":32,"value":33},{"source":72,"target":32,"value":33},{"source":120,"target":32,"value":33},{"source":155,"target":32,"value":33},{"source":156,"target":32,"value":33},{"source":157,"target":32,"value":33},{"source":158,"target":32,"value":33},{"source":196,"target":32,"value":33},{"source":33,"target":33,"value":34},{"source":73,"target":33,"value":34},{"source":120,"target":33,"value":34},{"source":155,"target":33,"value":34},{"source":156,"target":33,"value":34},{"source":157,"target":33,"value":34},{"source":158,"target":33,"value":34},{"source":197,"target":33,"value":34},{"source":34,"target":34,"value":35},{"source":74,"target":34,"value":35},{"source":120,"target":34,"value":35},{"source":155,"target":34,"value":35},{"source":156,"target":34,"value":35},{"source":157,"target":34,"value":35},{"source":158,"target":34,"value":35},{"source":198,"target":34,"value":35},{"source":35,"target":35,"value":36},{"source":75,"target":35,"value":36},{"source":120,"target":35,"value":36},{"source":155,"target":35,"value":36},{"source":156,"target":35,"value":36},{"source":157,"target":35,"value":36},{"source":158,"target":35,"value":36},{"source":159,"target":35,"value":36},{"source":160,"target":35,"value":36},{"source":161,"target":35,"value":36},{"source":162,"target":35,"value":36},{"source":199,"target":35,"value":36},{"source":36,"target":36,"value":37},{"source":76,"target":36,"value":37},{"source":120,"target":36,"value":37},{"source":159,"target":36,"value":37},{"source":160,"target":36,"value":37},{"source":161,"target":36,"value":37},{"source":162,"target":36,"value":37},{"source":200,"target":36,"value":37},{"source":37,"target":37,"value":38},{"source":77,"target":37,"value":38},{"source":120,"target":37,"value":38},{"source":159,"target":37,"value":38},{"source":160,"target":37,"value":38},{"source":161,"target":37,"value":38},{"source":162,"target":37,"value":38},{"source":201,"target":37,"value":38},{"source":38,"target":38,"value":39},{"source":78,"target":38,"value":39},{"source":120,"target":38,"value":39},{"source":159,"target":38,"value":39},{"source":160,"target":38,"value":39},{"source":161,"target":38,"value":39},{"source":162,"target":38,"value":39},{"source":202,"target":38,"value":39},{"source":39,"target":39,"value":40},{"source":159,"target":39,"value":40},{"source":160,"target":39,"value":40},{"source":161,"target":39,"value":40},{"source":162,"target":39,"value":40},{"source":40,"target":40,"value":41},{"source":81,"target":40,"value":41},{"source":120,"target":40,"value":41},{"source":124,"target":40,"value":41},{"source":163,"target":40,"value":41},{"source":164,"target":40,"value":41},{"source":165,"target":40,"value":41},{"source":166,"target":40,"value":41},{"source":41,"target":41,"value":42},{"source":82,"target":41,"value":42},{"source":120,"target":41,"value":42},{"source":125,"target":41,"value":42},{"source":163,"target":41,"value":42},{"source":164,"target":41,"value":42},{"source":165,"target":41,"value":42},{"source":166,"target":41,"value":42},{"source":42,"target":42,"value":43},{"source":83,"target":42,"value":43},{"source":120,"target":42,"value":43},{"source":126,"target":42,"value":43},{"source":163,"target":42,"value":43},{"source":164,"target":42,"value":43},{"source":165,"target":42,"value":43},{"source":166,"target":42,"value":43},{"source":43,"target":43,"value":44},{"source":84,"target":43,"value":44},{"source":120,"target":43,"value":44},{"source":127,"target":43,"value":44},{"source":163,"target":43,"value":44},{"source":164,"target":43,"value":44},{"source":165,"target":43,"value":44},{"source":166,"target":43,"value":44},{"source":167,"target":43,"value":44},{"source":168,"target":43,"value":44},{"source":169,"target":43,"value":44},{"source":170,"target":43,"value":44},{"source":44,"target":44,"value":45},{"source":85,"target":44,"value":45},{"source":120,"target":44,"value":45},{"source":128,"target":44,"value":45},{"source":167,"target":44,"value":45},{"source":168,"target":44,"value":45},{"source":169,"target":44,"value":45},{"source":170,"target":44,"value":45},{"source":45,"target":45,"value":46},{"source":86,"target":45,"value":46},{"source":120,"target":45,"value":46},{"source":129,"target":45,"value":46},{"source":167,"target":45,"value":46},{"source":168,"target":45,"value":46},{"source":169,"target":45,"value":46},{"source":170,"target":45,"value":46},{"source":46,"target":46,"value":47},{"source":87,"target":46,"value":47},{"source":120,"target":46,"value":47},{"source":130,"target":46,"value":47},{"source":167,"target":46,"value":47},{"source":168,"target":46,"value":47},{"source":169,"target":46,"value":47},{"source":170,"target":46,"value":47},{"source":47,"target":47,"value":48},{"source":88,"target":47,"value":48},{"source":120,"target":47,"value":48},{"source":131,"target":47,"value":48},{"source":167,"target":47,"value":48},{"source":168,"target":47,"value":48},{"source":169,"target":47,"value":48},{"source":170,"target":47,"value":48},{"source":171,"target":47,"value":48},{"source":172,"target":47,"value":48},{"source":173,"target":47,"value":48},{"source":174,"target":47,"value":48},{"source":48,"target":48,"value":49},{"source":89,"target":48,"value":49},{"source":120,"target":48,"value":49},{"source":132,"target":48,"value":49},{"source":171,"target":48,"value":49},{"source":172,"target":48,"value":49},{"source":173,"target":48,"value":49},{"source":174,"target":48,"value":49},{"source":49,"target":49,"value":50},{"source":90,"target":49,"value":50},{"source":120,"target":49,"value":50},{"source":133,"target":49,"value":50},{"source":171,"target":49,"value":50},{"source":172,"target":49,"value":50},{"source":173,"target":49,"value":50},{"source":174,"target":49,"value":50},{"source":50,"target":50,"value":51},{"source":91,"target":50,"value":51},{"source":120,"target":50,"value":51},{"source":134,"target":50,"value":51},{"source":171,"target":50,"value":51},{"source":172,"target":50,"value":51},{"source":173,"target":50,"value":51},{"source":174,"target":50,"value":51},{"source":51,"target":51,"value":52},{"source":92,"target":51,"value":52},{"source":120,"target":51,"value":52},{"source":135,"target":51,"value":52},{"source":171,"target":51,"value":52},{"source":172,"target":51,"value":52},{"source":173,"target":51,"value":52},{"source":174,"target":51,"value":52},{"source":175,"target":51,"value":52},{"source":176,"target":51,"value":52},{"source":177,"target":51,"value":52},{"source":178,"target":51,"value":52},{"source":52,"target":52,"value":53},{"source":93,"target":52,"value":53},{"source":120,"target":52,"value":53},{"source":136,"target":52,"value":53},{"source":175,"target":52,"value":53},{"source":176,"target":52,"value":53},{"source":177,"target":52,"value":53},{"source":178,"target":52,"value":53},{"source":53,"target":53,"value":54},{"source":94,"target":53,"value":54},{"source":120,"target":53,"value":54},{"source":137,"target":53,"value":54},{"source":175,"target":53,"value":54},{"source":176,"target":53,"value":54},{"source":177,"target":53,"value":54},{"source":178,"target":53,"value":54},{"source":54,"target":54,"value":55},{"source":95,"target":54,"value":55},{"source":120,"target":54,"value":55},{"source":138,"target":54,"value":55},{"source":175,"target":54,"value":55},{"source":176,"target":54,"value":55},{"source":177,"target":54,"value":55},{"source":178,"target":54,"value":55},{"source":55,"target":55,"value":56},{"source":96,"target":55,"value":56},{"source":120,"target":55,"value":56},{"source":139,"target":55,"value":56},{"source":175,"target":55,"value":56},{"source":176,"target":55,"value":56},{"source":177,"target":55,"value":56},{"source":178,"target":55,"value":56},{"source":179,"target":55,"value":56},{"source":180,"target":55,"value":56},{"source":181,"target":55,"value":56},{"source":182,"target":55,"value":56},{"source":56,"target":56,"value":57},{"source":97,"target":56,"value":57},{"source":120,"target":56,"value":57},{"source":140,"target":56,"value":57},{"source":179,"target":56,"value":57},{"source":180,"target":56,"value":57},{"source":181,"target":56,"value":57},{"source":182,"target":56,"value":57},{"source":57,"target":57,"value":58},{"source":98,"target":57,"value":58},{"source":120,"target":57,"value":58},{"source":141,"target":57,"value":58},{"source":179,"target":57,"value":58},{"source":180,"target":57,"value":58},{"source":181,"target":57,"value":58},{"source":182,"target":57,"value":58},{"source":58,"target":58,"value":59},{"source":99,"target":58,"value":59},{"source":120,"target":58,"value":59},{"source":142,"target":58,"value":59},{"source":179,"target":58,"value":59},{"source":180,"target":58,"value":59},{"source":181,"target":58,"value":59},{"source":182,"target":58,"value":59},{"source":59,"target":59,"value":60},{"source":100,"target":59,"value":60},{"source":120,"target":59,"value":60},{"source":143,"target":59,"value":60},{"source":179,"target":59,"value":60},{"source":180,"target":59,"value":60},{"source":181,"target":59,"value":60},{"source":182,"target":59,"value":60},{"source":183,"target":59,"value":60},{"source":184,"target":59,"value":60},{"source":185,"target":59,"value":60},{"source":186,"target":59,"value":60},{"source":60,"target":60,"value":61},{"source":101,"target":60,"value":61},{"source":120,"target":60,"value":61},{"source":144,"target":60,"value":61},{"source":183,"target":60,"value":61},{"source":184,"target":60,"value":61},{"source":185,"target":60,"value":61},{"source":186,"target":60,"value":61},{"source":61,"target":61,"value":62},{"source":102,"target":61,"value":62},{"source":120,"target":61,"value":62},{"source":145,"target":61,"value":62},{"source":183,"target":61,"value":62},{"source":184,"target":61,"value":62},{"source":185,"target":61,"value":62},{"source":186,"target":61,"value":62},{"source":62,"target":62,"value":63},{"source":103,"target":62,"value":63},{"source":120,"target":62,"value":63},{"source":146,"target":62,"value":63},{"source":183,"target":62,"value":63},{"source":184,"target":62,"value":63},{"source":185,"target":62,"value":63},{"source":186,"target":62,"value":63},{"source":63,"target":63,"value":64},{"source":104,"target":63,"value":64},{"source":120,"target":63,"value":64},{"source":147,"target":63,"value":64},{"source":183,"target":63,"value":64},{"source":184,"target":63,"value":64},{"source":185,"target":63,"value":64},{"source":186,"target":63,"value":64},{"source":187,"target":63,"value":64},{"source":188,"target":63,"value":64},{"source":189,"target":63,"value":64},{"source":190,"target":63,"value":64},{"source":64,"target":64,"value":65},{"source":105,"target":64,"value":65},{"source":120,"target":64,"value":65},{"source":148,"target":64,"value":65},{"source":187,"target":64,"value":65},{"source":188,"target":64,"value":65},{"source":189,"target":64,"value":65},{"source":190,"target":64,"value":65},{"source":65,"target":65,"value":66},{"source":106,"target":65,"value":66},{"source":120,"target":65,"value":66},{"source":149,"target":65,"value":66},{"source":187,"target":65,"value":66},{"source":188,"target":65,"value":66},{"source":189,"target":65,"value":66},{"source":190,"target":65,"value":66},{"source":66,"target":66,"value":67},{"source":107,"target":66,"value":67},{"source":120,"target":66,"value":67},{"source":150,"target":66,"value":67},{"source":187,"target":66,"value":67},{"source":188,"target":66,"value":67},{"source":189,"target":66,"value":67},{"source":190,"target":66,"value":67},{"source":67,"target":67,"value":68},{"source":108,"target":67,"value":68},{"source":120,"target":67,"value":68},{"source":151,"target":67,"value":68},{"source":187,"target":67,"value":68},{"source":188,"target":67,"value":68},{"source":189,"target":67,"value":68},{"source":190,"target":67,"value":68},{"source":191,"target":67,"value":68},{"source":192,"target":67,"value":68},{"source":193,"target":67,"value":68},{"source":194,"target":67,"value":68},{"source":68,"target":68,"value":69},{"source":109,"target":68,"value":69},{"source":120,"target":68,"value":69},{"source":152,"target":68,"value":69},{"source":191,"target":68,"value":69},{"source":192,"target":68,"value":69},{"source":193,"target":68,"value":69},{"source":194,"target":68,"value":69},{"source":69,"target":69,"value":70},{"source":110,"target":69,"value":70},{"source":120,"target":69,"value":70},{"source":153,"target":69,"value":70},{"source":191,"target":69,"value":70},{"source":192,"target":69,"value":70},{"source":193,"target":69,"value":70},{"source":194,"target":69,"value":70},{"source":70,"target":70,"value":71},{"source":111,"target":70,"value":71},{"source":120,"target":70,"value":71},{"source":154,"target":70,"value":71},{"source":191,"target":70,"value":71},{"source":192,"target":70,"value":71},{"source":193,"target":70,"value":71},{"source":194,"target":70,"value":71},{"source":71,"target":71,"value":72},{"source":112,"target":71,"value":72},{"source":120,"target":71,"value":72},{"source":155,"target":71,"value":72},{"source":191,"target":71,"value":72},{"source":192,"target":71,"value":72},{"source":193,"target":71,"value":72},{"source":194,"target":71,"value":72},{"source":195,"target":71,"value":72},{"source":196,"target":71,"value":72},{"source":197,"target":71,"value":72},{"source":198,"target":71,"value":72},{"source":72,"target":72,"value":73},{"source":113,"target":72,"value":73},{"source":120,"target":72,"value":73},{"source":156,"target":72,"value":73},{"source":195,"target":72,"value":73},{"source":196,"target":72,"value":73},{"source":197,"target":72,"value":73},{"source":198,"target":72,"value":73},{"source":73,"target":73,"value":74},{"source":114,"target":73,"value":74},{"source":120,"target":73,"value":74},{"source":157,"target":73,"value":74},{"source":195,"target":73,"value":74},{"source":196,"target":73,"value":74},{"source":197,"target":73,"value":74},{"source":198,"target":73,"value":74},{"source":74,"target":74,"value":75},{"source":115,"target":74,"value":75},{"source":120,"target":74,"value":75},{"source":158,"target":74,"value":75},{"source":195,"target":74,"value":75},{"source":196,"target":74,"value":75},{"source":197,"target":74,"value":75},{"source":198,"target":74,"value":75},{"source":75,"target":75,"value":76},{"source":116,"target":75,"value":76},{"source":120,"target":75,"value":76},{"source":159,"target":75,"value":76},{"source":195,"target":75,"value":76},{"source":196,"target":75,"value":76},{"source":197,"target":75,"value":76},{"source":198,"target":75,"value":76},{"source":199,"target":75,"value":76},{"source":200,"target":75,"value":76},{"source":201,"target":75,"value":76},{"source":202,"target":75,"value":76},{"source":76,"target":76,"value":77},{"source":117,"target":76,"value":77},{"source":120,"target":76,"value":77},{"source":160,"target":76,"value":77},{"source":199,"target":76,"value":77},{"source":200,"target":76,"value":77},{"source":201,"target":76,"value":77},{"source":202,"target":76,"value":77},{"source":77,"target":77,"value":78},{"source":118,"target":77,"value":78},{"source":120,"target":77,"value":78},{"source":161,"target":77,"value":78},{"source":199,"target":77,"value":78},{"source":200,"target":77,"value":78},{"source":201,"target":77,"value":78},{"source":202,"target":77,"value":78},{"source":78,"target":78,"value":79},{"source":119,"target":78,"value":79},{"source":120,"target":78,"value":79},{"source":162,"target":78,"value":79},{"source":199,"target":78,"value":79},{"source":200,"target":78,"value":79},{"source":201,"target":78,"value":79},{"source":202,"target":78,"value":79},{"source":79,"target":79,"value":80},{"source":199,"target":79,"value":80},{"source":200,"target":79,"value":80},{"source":201,"target":79,"value":80},{"source":202,"target":79,"value":80},{"source":80,"target":80,"value":81},{"source":120,"target":80,"value":81},{"source":163,"target":80,"value":81},{"source":203,"target":80,"value":81},{"source":81,"target":81,"value":82},{"source":120,"target":81,"value":82},{"source":164,"target":81,"value":82},{"source":203,"target":81,"value":82},{"source":82,"target":82,"value":83},{"source":120,"target":82,"value":83},{"source":165,"target":82,"value":83},{"source":203,"target":82,"value":83},{"source":83,"target":83,"value":84},{"source":120,"target":83,"value":84},{"source":166,"target":83,"value":84},{"source":203,"target":83,"value":84},{"source":84,"target":84,"value":85},{"source":120,"target":84,"value":85},{"source":167,"target":84,"value":85},{"source":203,"target":84,"value":85},{"source":85,"target":85,"value":86},{"source":120,"target":85,"value":86},{"source":168,"target":85,"value":86},{"source":203,"target":85,"value":86},{"source":86,"target":86,"value":87},{"source":120,"target":86,"value":87},{"source":169,"target":86,"value":87},{"source":203,"target":86,"value":87},{"source":87,"target":87,"value":88},{"source":120,"target":87,"value":88},{"source":170,"target":87,"value":88},{"source":203,"target":87,"value":88},{"source":88,"target":88,"value":89},{"source":120,"target":88,"value":89},{"source":171,"target":88,"value":89},{"source":203,"target":88,"value":89},{"source":89,"target":89,"value":90},{"source":120,"target":89,"value":90},{"source":172,"target":89,"value":90},{"source":203,"target":89,"value":90},{"source":90,"target":90,"value":91},{"source":120,"target":90,"value":91},{"source":173,"target":90,"value":91},{"source":203,"target":90,"value":91},{"source":91,"target":91,"value":92},{"source":120,"target":91,"value":92},{"source":174,"target":91,"value":92},{"source":203,"target":91,"value":92},{"source":92,"target":92,"value":93},{"source":120,"target":92,"value":93},{"source":175,"target":92,"value":93},{"source":203,"target":92,"value":93},{"source":93,"target":93,"value":94},{"source":120,"target":93,"value":94},{"source":176,"target":93,"value":94},{"source":203,"target":93,"value":94},{"source":94,"target":94,"value":95},{"source":120,"target":94,"value":95},{"source":177,"target":94,"value":95},{"source":203,"target":94,"value":95},{"source":95,"target":95,"value":96},{"source":120,"target":95,"value":96},{"source":178,"target":95,"value":96},{"source":203,"target":95,"value":96},{"source":96,"target":96,"value":97},{"source":120,"target":96,"value":97},{"source":179,"target":96,"value":97},{"source":203,"target":96,"value":97},{"source":97,"target":97,"value":98},{"source":120,"target":97,"value":98},{"source":180,"target":97,"value":98},{"source":203,"target":97,"value":98},{"source":98,"target":98,"value":99},{"source":120,"target":98,"value":99},{"source":181,"target":98,"value":99},{"source":203,"target":98,"value":99},{"source":99,"target":99,"value":100},{"source":120,"target":99,"value":100},{"source":182,"target":99,"value":100},{"source":203,"target":99,"value":100},{"source":100,"target":100,"value":101},{"source":120,"target":100,"value":101},{"source":183,"target":100,"value":101},{"source":203,"target":100,"value":101},{"source":101,"target":101,"value":102},{"source":120,"target":101,"value":102},{"source":184,"target":101,"value":102},{"source":203,"target":101,"value":102},{"source":102,"target":102,"value":103},{"source":120,"target":102,"value":103},{"source":185,"target":102,"value":103},{"source":203,"target":102,"value":103},{"source":103,"target":103,"value":104},{"source":120,"target":103,"value":104},{"source":186,"target":103,"value":104},{"source":203,"target":103,"value":104},{"source":104,"target":104,"value":105},{"source":120,"target":104,"value":105},{"source":187,"target":104,"value":105},{"source":203,"target":104,"value":105},{"source":105,"target":105,"value":106},{"source":120,"target":105,"value":106},{"source":188,"target":105,"value":106},{"source":203,"target":105,"value":106},{"source":106,"target":106,"value":107},{"source":120,"target":106,"value":107},{"source":189,"target":106,"value":107},{"source":203,"target":106,"value":107},{"source":107,"target":107,"value":108},{"source":120,"target":107,"value":108},{"source":190,"target":107,"value":108},{"source":203,"target":107,"value":108},{"source":108,"target":108,"value":109},{"source":120,"target":108,"value":109},{"source":191,"target":108,"value":109},{"source":203,"target":108,"value":109},{"source":109,"target":109,"value":110},{"source":120,"target":109,"value":110},{"source":192,"target":109,"value":110},{"source":203,"target":109,"value":110},{"source":110,"target":110,"value":111},{"source":120,"target":110,"value":111},{"source":193,"target":110,"value":111},{"source":203,"target":110,"value":111},{"source":111,"target":111,"value":112},{"source":120,"target":111,"value":112},{"source":194,"target":111,"value":112},{"source":203,"target":111,"value":112},{"source":112,"target":112,"value":113},{"source":120,"target":112,"value":113},{"source":195,"target":112,"value":113},{"source":203,"target":112,"value":113},{"source":113,"target":113,"value":114},{"source":120,"target":113,"value":114},{"source":196,"target":113,"value":114},{"source":203,"target":113,"value":114},{"source":114,"target":114,"value":115},{"source":120,"target":114,"value":115},{"source":197,"target":114,"value":115},{"source":203,"target":114,"value":115},{"source":115,"target":115,"value":116},{"source":120,"target":115,"value":116},{"source":198,"target":115,"value":116},{"source":203,"target":115,"value":116},{"source":116,"target":116,"value":117},{"source":120,"target":116,"value":117},{"source":199,"target":116,"value":117},{"source":203,"target":116,"value":117},{"source":117,"target":117,"value":118},{"source":120,"target":117,"value":118},{"source":200,"target":117,"value":118},{"source":203,"target":117,"value":118},{"source":118,"target":118,"value":119},{"source":120,"target":118,"value":119},{"source":201,"target":118,"value":119},{"source":203,"target":118,"value":119},{"source":119,"target":119,"value":120},{"source":120,"target":119,"value":120},{"source":202,"target":119,"value":120},{"source":203,"target":119,"value":120},{"source":120,"target":120,"value":121},{"source":123,"target":120,"value":121},{"source":124,"target":120,"value":121},{"source":125,"target":120,"value":121},{"source":126,"target":120,"value":121},{"source":127,"target":120,"value":121},{"source":128,"target":120,"value":121},{"source":129,"target":120,"value":121},{"source":130,"target":120,"value":121},{"source":131,"target":120,"value":121},{"source":132,"target":120,"value":121},{"source":133,"target":120,"value":121},{"source":134,"target":120,"value":121},{"source":135,"target":120,"value":121},{"source":136,"target":120,"value":121},{"source":137,"target":120,"value":121},{"source":138,"target":120,"value":121},{"source":139,"target":120,"value":121},{"source":140,"target":120,"value":121},{"source":141,"target":120,"value":121},{"source":142,"target":120,"value":121},{"source":143,"target":120,"value":121},{"source":144,"target":120,"value":121},{"source":145,"target":120,"value":121},{"source":146,"target":120,"value":121},{"source":147,"target":120,"value":121},{"source":148,"target":120,"value":121},{"source":149,"target":120,"value":121},{"source":150,"target":120,"value":121},{"source":151,"target":120,"value":121},{"source":152,"target":120,"value":121},{"source":153,"target":120,"value":121},{"source":154,"target":120,"value":121},{"source":155,"target":120,"value":121},{"source":156,"target":120,"value":121},{"source":157,"target":120,"value":121},{"source":158,"target":120,"value":121},{"source":159,"target":120,"value":121},{"source":160,"target":120,"value":121},{"source":161,"target":120,"value":121},{"source":162,"target":120,"value":121},{"source":163,"target":120,"value":121},{"source":164,"target":120,"value":121},{"source":165,"target":120,"value":121},{"source":166,"target":120,"value":121},{"source":167,"target":120,"value":121},{"source":168,"target":120,"value":121},{"source":169,"target":120,"value":121},{"source":170,"target":120,"value":121},{"source":171,"target":120,"value":121},{"source":172,"target":120,"value":121},{"source":173,"target":120,"value":121},{"source":174,"target":120,"value":121},{"source":175,"target":120,"value":121},{"source":176,"target":120,"value":121},{"source":177,"target":120,"value":121},{"source":178,"target":120,"value":121},{"source":179,"target":120,"value":121},{"source":180,"target":120,"value":121},{"source":181,"target":120,"value":121},{"source":182,"target":120,"value":121},{"source":183,"target":120,"value":121},{"source":184,"target":120,"value":121},{"source":185,"target":120,"value":121},{"source":186,"target":120,"value":121},{"source":187,"target":120,"value":121},{"source":188,"target":120,"value":121},{"source":189,"target":120,"value":121},{"source":190,"target":120,"value":121},{"source":191,"target":120,"value":121},{"source":192,"target":120,"value":121},{"source":193,"target":120,"value":121},{"source":194,"target":120,"value":121},{"source":195,"target":120,"value":121},{"source":196,"target":120,"value":121},{"source":197,"target":120,"value":121},{"source":198,"target":120,"value":121},{"source":199,"target":120,"value":121},{"source":200,"target":120,"value":121},{"source":201,"target":120,"value":121},{"source":202,"target":120,"value":121},{"source":203,"target":120,"value":121},{"source":204,"target":120,"value":121},{"source":121,"target":121,"value":122},{"source":203,"target":121,"value":122},{"source":122,"target":122,"value":123},{"source":204,"target":122,"value":123}]}